{
  "@context": [
    "https://www.w3.org/ns/did/v1"
  ],
  "id": "did:pai:638e94cf149842c1",
  "verificationMethod": [
    {
      "id": "did:pai:638e94cf149842c1#key-1",
      "type": "Ed25519VerificationKey2020",
      "controller": "did:pai:638e94cf149842c1",
      "publicKeyMultibase": "638e94cf149842c1b6710144b064df3bee09f9e508bbfe833ac8a4cd7fe181cd"
    }
  ],
  "authentication": [
    "did:pai:638e94cf149842c1#key-1"
  ],
  "service": [
    {
      "id": "#pai-bridge",
      "type": "PAIUniversalBridge",
      "serviceEndpoint": "local://bin/pai"
    }
  ]
}